MANIFEST.in
README.md
setup.py
winsible/__init__.py
winsible/paramiko_pool.py
winsible/plink.exe
winsible/plink.py
winsible/pscp.exe
winsible/psftp.exe
winsible/putty.exe
winsible.egg-info/PKG-INFO
winsible.egg-info/SOURCES.txt
winsible.egg-info/dependency_links.txt
winsible.egg-info/entry_points.txt
winsible.egg-info/not-zip-safe
winsible.egg-info/requires.txt
winsible.egg-info/top_level.txt
winsible/sessions/ansible_cygwin_plink