Metadata-Version: 1.0
Name: winsible
Version: 0.1.0
Summary: A faster `ansible` For The (cyg)Win (and other platforms)
Home-page: https://github.com/pjeby/winsible
Author: PJ Eby
Author-email: peak@eby-sarna.com
License: MIT
Keywords: ansible ssh cygwin
Platform: UNKNOWN
